deadnews_python_template/__init__.py
deadnews_python_template-1.0.1.dist-info/LICENSE
deadnews_python_template-1.0.1.dist-info/WHEEL
deadnews_python_template-1.0.1.dist-info/METADATA
deadnews_python_template-1.0.1.dist-info/RECORD
