Metadata-Version: 2.1
Name: deadnews-python-template
Version: 1.0.1
Summary: Python Project Template
Home-page: https://github.com/DeadNews/deadnews-python-template
License: MIT
Keywords: python,template,layout
Author: DeadNews
Author-email: uhjnnn@gmail.com
Requires-Python: >=3.9,<4.0
Classifier: License :: OSI Approved :: MIT License
Classifier: Operating System :: OS Independent
Classifier: Programming Language :: Python :: 3
Classifier: Programming Language :: Python :: 3.9
Classifier: Programming Language :: Python :: 3.10
Classifier: Programming Language :: Python :: 3.11
Project-URL: Repository, https://github.com/DeadNews/deadnews-python-template
